dd_import/__init__.py
dd_import/dd_api.py
dd_import/dd_import_languages.py
dd_import/dd_reimport_findings.py
dd_import/environment.py
dd_import-1.0.12.dist-info/LICENSE.txt
dd_import-1.0.12.dist-info/METADATA
dd_import-1.0.12.dist-info/WHEEL
dd_import-1.0.12.dist-info/entry_points.txt
dd_import-1.0.12.dist-info/top_level.txt
dd_import-1.0.12.dist-info/RECORD
