Metadata-Version: 2.1
Name: dd-import
Version: 1.0.12
Summary: A utility to (re-)import findings and language data into DefectDojo
Home-page: https://github.com/MaibornWolff/dd-import
Author: Stefan Fleckenstein
Author-email: stefan.fleckenstein@maibornwolff.de
Project-URL: Issue Tracker, https://github.com/MaibornWolff/dd-import/issues
Classifier: Programming Language :: Python :: 3
Classifier: License :: OSI Approved :: BSD License
Classifier: Operating System :: OS Independent
Requires-Python: >=3.8
License-File: LICENSE.txt
Requires-Dist: requests >=2.26.0
